{"config": {"view": {"continuousWidth": 400, "continuousHeight": 300}, "axis": {"gridColor": "grey", "gridDash": [6, 4]}, "axisBottom": {"labelColor": "#c83803", "labelFontSize": 15, "titleColor": "#c83803", "titleFontSize": 17}, "axisLeft": {"labelColor": "#c83803", "labelFontSize": 15, "titleColor": "#c83803", "titleFontSize": 17}, "background": "#0B162A", "legend": {"cornerRadius": 10, "fillColor": "#0B162A", "labelColor": "#c83803", "labelFontSize": 15, "orient": "top-right", "padding": 10, "strokeColor": "gray", "titleColor": "#c83803", "titleFontSize": 15}, "title": {"color": "#c83803", "fontSize": 25}}, "layer": [{"mark": "bar", "encoding": {"color": {"condition": {"value": "#c83803", "test": "((datum.score_diff - datum.num_spread) > 0)"}, "value": "white"}, "tooltip": [{"field": "Date", "type": "nominal"}, {"field": "Time (ET)", "type": "nominal"}, {"field": "Day", "type": "nominal"}, {"field": "Favorite", "type": "nominal"}, {"field": "Underdog", "type": "nominal"}, {"field": "Over/Under", "type": "nominal"}, {"field": "Spread", "type": "nominal"}, {"field": "Score", "type": "nominal"}, {"field": "score_diff", "type": "quantitative"}, {"field": "spread_v_result", "type": "quantitative"}], "x": {"field": "matchup", "title": "Fav - Dog", "type": "nominal"}, "y": {"field": "score_diff", "title": "Score Differential (Dog pts - Fav pts) and Spread", "type": "quantitative"}}, "height": 500, "title": "Week 8 Score Differential Vs Game Spread", "width": 800}, {"mark": {"type": "tick", "color": "red", "size": 36.0, "thickness": 5, "width": 50}, "encoding": {"x": {"field": "matchup", "title": "Fav - Dog", "type": "nominal"}, "y": {"field": "num_spread", "type": "quantitative"}}}], "data": {"name": "data-bbee19aeeeec6f561e3166e2076826ec"}, "$schema": "https://vega.github.io/schema/vega-lite/v4.17.0.json", "datasets": {"data-bbee19aeeeec6f561e3166e2076826ec": [{"Unnamed: 0": 0, "Day": "Thu", "Date": "Oct 27, 2022", "Time (ET)": "8:15", "Unnamed: 4": "@", "Favorite": "Tampa Bay Buccaneers", "Score": "L 22-27", "Spread": "L -1.5", "Unnamed: 8": null, "Underdog": "Baltimore Ravens", "Over/Under": "O 45.5", "Notes": null, "week": 8, "result_ats": "L", "spread": "-1.5", "result": "L", "fav_pts": "22", "opp_pts": "27", "num_spread": -1.5, "score_diff": 5, "fav_abr": "TB", "dog_abr": "Bal", "matchup": "TB vs Bal", "fav_covered": true, "spread_v_result": 6.5}, {"Unnamed: 0": 1, "Day": "Sun", "Date": "Oct 30, 2022", "Time (ET)": "9:29", "Unnamed: 4": "N", "Favorite": "Jacksonville Jaguars", "Score": "L 17-21", "Spread": "L -2", "Unnamed: 8": null, "Underdog": "Denver Broncos", "Over/Under": "U 40.5", "Notes": "at London", "week": 8, "result_ats": "L", "spread": "-2", "result": "L", "fav_pts": "17", "opp_pts": "21", "num_spread": -2.0, "score_diff": 4, "fav_abr": "Jac", "dog_abr": "Den", "matchup": "Jac vs Den", "fav_covered": true, "spread_v_result": 6.0}, {"Unnamed: 0": 2, "Day": "Sun", "Date": "Oct 30, 2022", "Time (ET)": "1:00", "Unnamed: 4": "@", "Favorite": "Atlanta Falcons", "Score": "W 37-34 (OT)", "Spread": "L -4", "Unnamed: 8": null, "Underdog": "Carolina Panthers", "Over/Under": "O 41", "Notes": null, "week": 8, "result_ats": "L", "spread": "-4", "result": "W", "fav_pts": "37", "opp_pts": "34", "num_spread": -4.0, "score_diff": -3, "fav_abr": "Atl", "dog_abr": "Car", "matchup": "Atl vs Car", "fav_covered": true, "spread_v_result": 1.0}, {"Unnamed: 0": 3, "Day": "Sun", "Date": "Oct 30, 2022", "Time (ET)": "1:00", "Unnamed: 4": "@", "Favorite": "Dallas Cowboys", "Score": "W 49-29", "Spread": "W -10", "Unnamed: 8": null, "Underdog": "Chicago Bears", "Over/Under": "O 42.5", "Notes": null, "week": 8, "result_ats": "W", "spread": "-10", "result": "W", "fav_pts": "49", "opp_pts": "29", "num_spread": -10.0, "score_diff": -20, "fav_abr": "Dal", "dog_abr": "Chi", "matchup": "Dal vs Chi", "fav_covered": false, "spread_v_result": -10.0}, {"Unnamed: 0": 4, "Day": "Sun", "Date": "Oct 30, 2022", "Time (ET)": "1:00", "Unnamed: 4": null, "Favorite": "Miami Dolphins", "Score": "W 31-27", "Spread": "W -3.5", "Unnamed: 8": "@", "Underdog": "Detroit Lions", "Over/Under": "O 51.5", "Notes": null, "week": 8, "result_ats": "W", "spread": "-3.5", "result": "W", "fav_pts": "31", "opp_pts": "27", "num_spread": -3.5, "score_diff": -4, "fav_abr": "Mia", "dog_abr": "Det", "matchup": "Mia vs Det", "fav_covered": false, "spread_v_result": -0.5}, {"Unnamed: 0": 5, "Day": "Sun", "Date": "Oct 30, 2022", "Time (ET)": "1:00", "Unnamed: 4": "@", "Favorite": "Minnesota Vikings", "Score": "W 34-26", "Spread": "W -3.5", "Unnamed: 8": null, "Underdog": "Arizona Cardinals", "Over/Under": "O 48.5", "Notes": null, "week": 8, "result_ats": "W", "spread": "-3.5", "result": "W", "fav_pts": "34", "opp_pts": "26", "num_spread": -3.5, "score_diff": -8, "fav_abr": "Min", "dog_abr": "Az", "matchup": "Min vs Az", "fav_covered": false, "spread_v_result": -4.5}, {"Unnamed: 0": 6, "Day": "Sun", "Date": "Oct 30, 2022", "Time (ET)": "1:00", "Unnamed: 4": null, "Favorite": "Las Vegas Raiders", "Score": "L 0-24", "Spread": "L -1.5", "Unnamed: 8": "@", "Underdog": "New Orleans Saints", "Over/Under": "U 49.5", "Notes": null, "week": 8, "result_ats": "L", "spread": "-1.5", "result": "L", "fav_pts": "0", "opp_pts": "24", "num_spread": -1.5, "score_diff": 24, "fav_abr": "LV", "dog_abr": "No", "matchup": "LV vs No", "fav_covered": true, "spread_v_result": 25.5}, {"Unnamed: 0": 7, "Day": "Sun", "Date": "Oct 30, 2022", "Time (ET)": "1:00", "Unnamed: 4": null, "Favorite": "New England Patriots", "Score": "W 22-17", "Spread": "W -2.5", "Unnamed: 8": "@", "Underdog": "New York Jets", "Over/Under": "U 40", "Notes": null, "week": 8, "result_ats": "W", "spread": "-2.5", "result": "W", "fav_pts": "22", "opp_pts": "17", "num_spread": -2.5, "score_diff": -5, "fav_abr": "NE", "dog_abr": "Jets", "matchup": "NE vs Jets", "fav_covered": false, "spread_v_result": -2.5}, {"Unnamed: 0": 8, "Day": "Sun", "Date": "Oct 30, 2022", "Time (ET)": "1:00", "Unnamed: 4": "@", "Favorite": "Philadelphia Eagles", "Score": "W 35-13", "Spread": "W -10.5", "Unnamed: 8": null, "Underdog": "Pittsburgh Steelers", "Over/Under": "O 43", "Notes": null, "week": 8, "result_ats": "W", "spread": "-10.5", "result": "W", "fav_pts": "35", "opp_pts": "13", "num_spread": -10.5, "score_diff": -22, "fav_abr": "Phi", "dog_abr": "Pit", "matchup": "Phi vs Pit", "fav_covered": false, "spread_v_result": -11.5}, {"Unnamed: 0": 9, "Day": "Sun", "Date": "Oct 30, 2022", "Time (ET)": "4:04", "Unnamed: 4": null, "Favorite": "Tennessee Titans", "Score": "W 17-10", "Spread": "W -3.5", "Unnamed: 8": "@", "Underdog": "Houston Texans", "Over/Under": "U 39", "Notes": null, "week": 8, "result_ats": "W", "spread": "-3.5", "result": "W", "fav_pts": "17", "opp_pts": "10", "num_spread": -3.5, "score_diff": -7, "fav_abr": "Ten", "dog_abr": "Hou", "matchup": "Ten vs Hou", "fav_covered": false, "spread_v_result": -3.5}, {"Unnamed: 0": 10, "Day": "Sun", "Date": "Oct 30, 2022", "Time (ET)": "4:04", "Unnamed: 4": "@", "Favorite": "Seattle Seahawks", "Score": "W 27-13", "Spread": "W -3", "Unnamed: 8": null, "Underdog": "New York Giants", "Over/Under": "U 44.5", "Notes": null, "week": 8, "result_ats": "W", "spread": "-3", "result": "W", "fav_pts": "27", "opp_pts": "13", "num_spread": -3.0, "score_diff": -14, "fav_abr": "Sea", "dog_abr": "Giants", "matchup": "Sea vs Giants", "fav_covered": false, "spread_v_result": -11.0}, {"Unnamed: 0": 11, "Day": "Sun", "Date": "Oct 30, 2022", "Time (ET)": "4:25", "Unnamed: 4": "@", "Favorite": "Indianapolis Colts", "Score": "L 16-17", "Spread": "L -3", "Unnamed: 8": null, "Underdog": "Washington Commanders", "Over/Under": "U 39.5", "Notes": null, "week": 8, "result_ats": "L", "spread": "-3", "result": "L", "fav_pts": "16", "opp_pts": "17", "num_spread": -3.0, "score_diff": 1, "fav_abr": "Ind", "dog_abr": "Was", "matchup": "Ind vs Was", "fav_covered": true, "spread_v_result": 4.0}, {"Unnamed: 0": 12, "Day": "Sun", "Date": "Oct 30, 2022", "Time (ET)": "4:25", "Unnamed: 4": "@", "Favorite": "Los Angeles Rams", "Score": "L 14-31", "Spread": "L -2.5", "Unnamed: 8": null, "Underdog": "San Francisco 49ers", "Over/Under": "O 42", "Notes": null, "week": 8, "result_ats": "L", "spread": "-2.5", "result": "L", "fav_pts": "14", "opp_pts": "31", "num_spread": -2.5, "score_diff": 17, "fav_abr": "Rams", "dog_abr": "SF", "matchup": "Rams vs SF", "fav_covered": true, "spread_v_result": 19.5}, {"Unnamed: 0": 13, "Day": "Sun", "Date": "Oct 30, 2022", "Time (ET)": "8:20", "Unnamed: 4": "@", "Favorite": "Buffalo Bills", "Score": "W 27-17", "Spread": "L -10.5", "Unnamed: 8": null, "Underdog": "Green Bay Packers", "Over/Under": "U 47", "Notes": null, "week": 8, "result_ats": "L", "spread": "-10.5", "result": "W", "fav_pts": "27", "opp_pts": "17", "num_spread": -10.5, "score_diff": -10, "fav_abr": "Buf", "dog_abr": "GB", "matchup": "Buf vs GB", "fav_covered": true, "spread_v_result": 0.5}, {"Unnamed: 0": 14, "Day": "Mon", "Date": "Oct 31, 2022", "Time (ET)": "8:15", "Unnamed: 4": null, "Favorite": "Cincinnati Bengals", "Score": "L 13-32", "Spread": "L -3", "Unnamed: 8": "@", "Underdog": "Cleveland Browns", "Over/Under": "P 45", "Notes": null, "week": 8, "result_ats": "L", "spread": "-3", "result": "L", "fav_pts": "13", "opp_pts": "32", "num_spread": -3.0, "score_diff": 19, "fav_abr": "Cin", "dog_abr": "Cle", "matchup": "Cin vs Cle", "fav_covered": true, "spread_v_result": 22.0}]}}